hexalate/__init__.py
hexalate/__main__.py
hexalate/hexalate.py
hexalate-0.1.0.dist-info/METADATA
hexalate-0.1.0.dist-info/WHEEL
hexalate-0.1.0.dist-info/entry_points.txt
hexalate-0.1.0.dist-info/RECORD
