Metadata-Version: 2.1
Name: hexalate
Version: 0.1.0
Summary: Create a tessellation with the desired width, height, and hexagon size
Home-page: https://github.com/james-see/hexalate
License: MIT
Keywords: hexagon,tessellation,geometry
Author: James Campbell
Author-email: james@jamescampbell.us
Requires-Python: >=3.11,<4.0
Classifier: Development Status :: 3 - Alpha
Classifier: Intended Audience :: Science/Research
Classifier: License :: OSI Approved :: MIT License
Classifier: Programming Language :: Python :: 3
Classifier: Programming Language :: Python :: 3.11
Classifier: Programming Language :: Python :: 3.12
Requires-Dist: argparse (>=1.4.0,<2.0.0)
Requires-Dist: matplotlib (>=3.9.2,<4.0.0)
Requires-Dist: numpy (>=2.1.0,<3.0.0)
Project-URL: Repository, https://github.com/james-see/hexalate
